bdpy/__init__.py
bdpy/bdata/__init__.py
bdpy/bdata/bdata.py
bdpy/bdata/featureselector.py
bdpy/bdata/metadata.py
bdpy/bdata/utils.py
bdpy/dataform/__init__.py
bdpy/dataform/datastore.py
bdpy/dataform/features.py
bdpy/dataform/kvs.py
bdpy/dataform/pd.py
bdpy/dataform/sparse.py
bdpy/dataform/utils.py
bdpy/dataset/__init__.py
bdpy/dataset/utils.py
bdpy/distcomp/__init__.py
bdpy/distcomp/distcomp.py
bdpy/dl/__init__.py
bdpy/dl/caffe.py
bdpy/dl/torch/__init__.py
bdpy/dl/torch/base.py
bdpy/dl/torch/dataset.py
bdpy/dl/torch/models.py
bdpy/dl/torch/torch.py
bdpy/dl/torch/domain/__init__.py
bdpy/dl/torch/domain/core.py
bdpy/dl/torch/domain/feature_domain.py
bdpy/dl/torch/domain/image_domain.py
bdpy/evals/__init__.py
bdpy/evals/metrics.py
bdpy/feature/__init__.py
bdpy/feature/feature.py
bdpy/fig/__init__.py
bdpy/fig/draw_group_image_set.py
bdpy/fig/fig.py
bdpy/fig/makeplots.py
bdpy/fig/makeplots2.py
bdpy/fig/tile_images.py
bdpy/ml/__init__.py
bdpy/ml/crossvalidation.py
bdpy/ml/ensemble.py
bdpy/ml/learning.py
bdpy/ml/model.py
bdpy/ml/regress.py
bdpy/ml/searchlight.py
bdpy/mri/__init__.py
bdpy/mri/fmriprep.py
bdpy/mri/glm.py
bdpy/mri/image.py
bdpy/mri/load_epi.py
bdpy/mri/load_mri.py
bdpy/mri/roi.py
bdpy/mri/spm.py
bdpy/opendata/__init__.py
bdpy/opendata/openneuro.py
bdpy/pipeline/config.py
bdpy/preproc/__init__.py
bdpy/preproc/interface.py
bdpy/preproc/preprocessor.py
bdpy/preproc/select_top.py
bdpy/preproc/util.py
bdpy/recon/__init__.py
bdpy/recon/utils.py
bdpy/recon/torch/__init__.py
bdpy/recon/torch/icnn.py
bdpy/recon/torch/modules/__init__.py
bdpy/recon/torch/modules/critic.py
bdpy/recon/torch/modules/encoder.py
bdpy/recon/torch/modules/generator.py
bdpy/recon/torch/modules/latent.py
bdpy/recon/torch/task/__init__.py
bdpy/recon/torch/task/inversion.py
bdpy/stats/__init__.py
bdpy/stats/corr.py
bdpy/task/__init__.py
bdpy/task/callback.py
bdpy/task/core.py
bdpy/util/__init__.py
bdpy/util/info.py
bdpy/util/math.py
bdpy/util/utils.py
bdpy-0.25.1.dist-info/METADATA
bdpy-0.25.1.dist-info/WHEEL
bdpy-0.25.1.dist-info/licenses/LICENSE
bdpy-0.25.1.dist-info/RECORD
