Metadata-Version: 2.3
Name: bdpy
Version: 0.25.1
Summary: Brain decoder toolbox for Python
Project-URL: Homepage, https://github.com/KamitaniLab/bdpy
Project-URL: Repository, https://github.com/KamitaniLab/bdpy
Project-URL: Bug Tracker, https://github.com/KamitaniLab/bdpy/issues
Author-email: "Shuntaro C. Aoki" <s_aoki@i.kyoto-u.ac.jp>
License: MIT License
License-File: LICENSE
Keywords: brain decoding,fmri,machine learning,neuroimaging,neuroscience
Requires-Python: <3.12,>=3.6
Requires-Dist: h5py
Requires-Dist: hdf5storage
Requires-Dist: numpy>=1.20
Requires-Dist: pandas
Requires-Dist: pyyaml
Requires-Dist: scikit-learn
Requires-Dist: scipy
Requires-Dist: tqdm
Provides-Extra: all
Requires-Dist: hydra-core; extra == 'all'
Requires-Dist: matplotlib; extra == 'all'
Requires-Dist: nibabel==3.2; extra == 'all'
Requires-Dist: nipy; extra == 'all'
Requires-Dist: numpy<1.24; extra == 'all'
Requires-Dist: omegaconf; extra == 'all'
Requires-Dist: pillow; extra == 'all'
Requires-Dist: torch; extra == 'all'
Requires-Dist: torchvision; extra == 'all'
Provides-Extra: caffe
Requires-Dist: pillow; extra == 'caffe'
Provides-Extra: dev
Requires-Dist: fastl2lir; extra == 'dev'
Requires-Dist: hydra-core; extra == 'dev'
Requires-Dist: matplotlib; extra == 'dev'
Requires-Dist: nibabel==3.2; extra == 'dev'
Requires-Dist: nipy; extra == 'dev'
Requires-Dist: numpy<1.24; extra == 'dev'
Requires-Dist: omegaconf; extra == 'dev'
Requires-Dist: pillow; extra == 'dev'
Requires-Dist: torch; extra == 'dev'
Requires-Dist: torchvision; extra == 'dev'
Provides-Extra: fig
Requires-Dist: matplotlib; extra == 'fig'
Requires-Dist: pillow; extra == 'fig'
Provides-Extra: mri
Requires-Dist: nibabel==3.2; extra == 'mri'
Requires-Dist: nipy; extra == 'mri'
Requires-Dist: numpy<1.24; extra == 'mri'
Provides-Extra: pipeline
Requires-Dist: hydra-core; extra == 'pipeline'
Requires-Dist: omegaconf; extra == 'pipeline'
Provides-Extra: torch
Requires-Dist: pillow; extra == 'torch'
Requires-Dist: torch; extra == 'torch'
Requires-Dist: torchvision; extra == 'torch'
